msikeys
