Metadata-Version: 1.1
Name: msikeys
Version: 0.0.3
Summary: Python MSI Keys
